viser/__init__.py
viser/_assignable_props_api.py
viser/_backwards_compat_shims.py
viser/_client_autobuild.py
viser/_gui_api.py
viser/_gui_handles.py
viser/_icons.py
viser/_icons_enum.py
viser/_icons_enum.pyi
viser/_icons_generate_enum.py
viser/_image_encoding.py
viser/_messages.py
viser/_notification_handle.py
viser/_scene_api.py
viser/_scene_handles.py
viser/_threadpool_exceptions.py
viser/_tunnel.py
viser/_viser.py
viser/py.typed
viser/_icons/tabler-icons.zip
viser/client/.eslintrc.js
viser/client/.gitignore
viser/client/index.html
viser/client/package-lock.json
viser/client/package.json
viser/client/postcss.config.cjs
viser/client/tsconfig.json
viser/client/vite-env.d.ts
viser/client/vite.config.mts
"viser/client/build/Inter-VariableFont_slnt,wght.ttf"
viser/client/build/index.html
viser/client/build/logo.svg
viser/client/build/manifest.json
viser/client/build/robots.txt
viser/client/build/assets/Sorter-Df0J3ZWJ.wasm
viser/client/build/assets/SplatSortWorker-D00osGmu.js
viser/client/build/assets/WebsocketServerWorker-C9fS7jGc.js
viser/client/build/assets/__vite-browser-external-BIHI7g3E.js
viser/client/build/assets/index-BebVY2FL.css
viser/client/build/assets/index-BqCrgzll.js
viser/client/build/hdri/dikhololo_night_1k.hdr
viser/client/build/hdri/empty_warehouse_01_1k.hdr
viser/client/build/hdri/forest_slope_1k.hdr
viser/client/build/hdri/kiara_1_dawn_1k.hdr
viser/client/build/hdri/lebombo_1k.hdr
viser/client/build/hdri/potsdamer_platz_1k.hdr
viser/client/build/hdri/rooitou_park_1k.hdr
viser/client/build/hdri/st_fagans_interior_1k.hdr
viser/client/build/hdri/studio_small_03_1k.hdr
viser/client/build/hdri/venice_sunset_1k.hdr
"viser/client/public/Inter-VariableFont_slnt,wght.ttf"
viser/client/public/logo.svg
viser/client/public/manifest.json
viser/client/public/robots.txt
viser/client/public/hdri/dikhololo_night_1k.hdr
viser/client/public/hdri/empty_warehouse_01_1k.hdr
viser/client/public/hdri/forest_slope_1k.hdr
viser/client/public/hdri/kiara_1_dawn_1k.hdr
viser3d-1.0.19.dist-info/METADATA
viser3d-1.0.19.dist-info/WHEEL
viser3d-1.0.19.dist-info/entry_points.txt
viser3d-1.0.19.dist-info/licenses/LICENSE
viser3d-1.0.19.dist-info/RECORD
