Metadata-Version: 2.4
Name: viser3d
Version: 1.0.19
Summary: 3D visualization + Python
Project-URL: GitHub, https://github.com/nerfstudio-project/viser
License: MIT
License-File: LICENSE
Classifier: License :: OSI Approved :: MIT License
Classifier: Operating System :: OS Independent
Classifier: Programming Language :: Python :: 3
Classifier: Programming Language :: Python :: 3.8
Classifier: Programming Language :: Python :: 3.9
Classifier: Programming Language :: Python :: 3.10
Classifier: Programming Language :: Python :: 3.11
Classifier: Programming Language :: Python :: 3.12
Classifier: Programming Language :: Python :: 3.13
Requires-Python: >=3.8
Requires-Dist: imageio<3.0.0,>=2.0.0
Requires-Dist: msgspec<1.0.0,>=0.18.6
Requires-Dist: nodeenv<2.0.0,>=1.9.1
Requires-Dist: numpy<3.0.0,>=1.0.0
Requires-Dist: requests<3.0.0,>=2.0.0
Requires-Dist: rich<15.0.0,>=13.3.3
Requires-Dist: tqdm<5.0.0,>=4.0.0
Requires-Dist: trimesh<5.0.0,>=3.21.7
Requires-Dist: typing-extensions>=4.0.0
Requires-Dist: websockets<16.0.0,>=13.1
Requires-Dist: yourdfpy<1.0.0,>=0.0.53
Provides-Extra: dev
Requires-Dist: hypothesis[numpy]; extra == 'dev'
Requires-Dist: opencv-python<5.0.0,>=4.0.0.21; extra == 'dev'
Requires-Dist: pre-commit==3.3.2; extra == 'dev'
Requires-Dist: psutil<8.0.0,>=5.9.5; extra == 'dev'
Requires-Dist: pyright>=1.1.308; extra == 'dev'
Requires-Dist: pytest; extra == 'dev'
Requires-Dist: ruff>=0.9.3; extra == 'dev'
Provides-Extra: examples
Requires-Dist: gdown>=4.6.6; extra == 'examples'
Requires-Dist: matplotlib>=3.7.1; extra == 'examples'
Requires-Dist: opencv-python; extra == 'examples'
Requires-Dist: pandas; extra == 'examples'
Requires-Dist: plotly>=5.21.0; extra == 'examples'
Requires-Dist: plyfile; extra == 'examples'
Requires-Dist: pyliblzfse>=0.4.1; (platform_system != 'Windows') and extra == 'examples'
Requires-Dist: robot-descriptions>=1.18.0; extra == 'examples'
Requires-Dist: torch>=1.13.1; extra == 'examples'
Requires-Dist: tyro<1.0.0,>=0.2.0; extra == 'examples'
